symbol_parser/__init__.py
symbol_parser/conventions.json
symbol_parser/parse_conventions_table.py
symbol_parser/suffix_regs.py
symbol_parser/symbol.py
symbol_parser/utils.py
symbol_parser-1.0.0.dist-info/WHEEL
symbol_parser-1.0.0.dist-info/METADATA
symbol_parser-1.0.0.dist-info/RECORD
