Metadata-Version: 2.1
Name: symbol-parser
Version: 1.0.0
Summary: Utility for parsing ticker symbols and converting symbol syntax to different conventions.
Home-page: https://github.com/danklabs-dev/symbol-parser
License: MIT
Author: Dan Kelleher
Author-email: kelleherjdan@gmail.com
Requires-Python: >=3.8.1,<4.0.0
Classifier: License :: OSI Approved :: MIT License
Classifier: Programming Language :: Python
Classifier: Programming Language :: Python :: 3
Classifier: Programming Language :: Python :: 3.9
Classifier: Programming Language :: Python :: 3.10
Classifier: Programming Language :: Python :: 3.11
Classifier: Programming Language :: Python :: 3
Classifier: Topic :: Software Development
Classifier: Topic :: Software Development :: Libraries
Classifier: Topic :: Software Development :: Libraries :: Python Modules
Classifier: Topic :: System :: Logging
Requires-Dist: lxml (>=4.8.0,<5.0.0)
Requires-Dist: requests (>=2.27.1,<3.0.0)
Project-URL: Repository, https://github.com/danklabs-dev/symbol-parser
